Workbook

Sheet Dashboard
A1: India Green Bond & ESG Loan Tracker
A2: Labelled green, ESG and sustainability-linked debt by Indian issuers, Jan 2023 - Oct 2026. Totals count completed deals (Priced, Signed, Devolved) in USD mn at FX-sheet rates.
A4: Completed deals | B4: =COUNTIFS(Deals!$Q$2:$Q$41,"Priced")+COUNTIFS(Deals!$Q$2:$Q$41,"Signed")+COUNTIFS(Deals!$Q$2:$Q$41,"Devolved") -> 23
A5: Total raised (USD mn) | B5: =SUMIFS(Deals!$J$2:$J$41,Deals!$Q$2:$Q$41,"Priced")+SUMIFS(Deals!$J$2:$J$41,Deals!$Q$2:$Q$41,"Signed")+SUMIFS(Deals!$J$2:$J$41,Deals!$Q$2:$Q$41,"Devolved") -> 6034.9656
A6: Total raised (INR crore) | B6: =B5*FX!$B$5/10 -> 53107.698
A7: Largest completed deal (USD mn) | B7: =MAX(_xlfn.MAXIFS(Deals!$J$2:$J$41,Deals!$Q$2:$Q$41,"Priced"),_xlfn.MAXIFS(Deals!$J$2:$J$41,Deals!$Q$2:$Q$41,"Signed"),_xlfn.MAXIFS(Deals!$J$2:$J$41,Deals!$Q$2:$Q$41,"Devolved")) -> 909.09091
A8: Sovereign green bonds outstanding (INR bn, Aug 2026) | B8: 877 | C8: Source: Reuters via Business Recorder, 14 Aug 2026
A10: By instrument | B10: Deals | C10: USD mn | D10: Share
A11: Green bond | B11: =COUNTIFS(Deals!$Q$2:$Q$41,"Priced",Deals!$F$2:$F$41,$A11)+COUNTIFS(Deals!$Q$2:$Q$41,"Signed",Deals!$F$2:$F$41,$A11)+COUNTIFS(Deals!$Q$2:$Q$41,"Devolved",Deals!$F$2:$F$41,$A11) -> 12 | C11: =SUMIFS(Deals!$J$2:$J$41,Deals!$Q$2:$Q$41,"Priced",Deals!$F$2:$F$41,$A11)+SUMIFS(Deals!$J$2:$J$41,Deals!$Q$2:$Q$41,"Signed",Deals!$F$2:$F$41,$A11)+SUMIFS(Deals!$J$2:$J$41,Deals!$Q$2:$Q$41,"Devolved",Deals!$F$2:$F$41,$A11) -> 3119.6591 | D11: =IF($B$5=0,0,C11/$B$5) -> 0.51693071
A12: ESG bond | B12: =COUNTIFS(Deals!$Q$2:$Q$41,"Priced",Deals!$F$2:$F$41,$A12)+COUNTIFS(Deals!$Q$2:$Q$41,"Signed",Deals!$F$2:$F$41,$A12)+COUNTIFS(Deals!$Q$2:$Q$41,"Devolved",Deals!$F$2:$F$41,$A12) -> 1 | C12: =SUMIFS(Deals!$J$2:$J$41,Deals!$Q$2:$Q$41,"Priced",Deals!$F$2:$F$41,$A12)+SUMIFS(Deals!$J$2:$J$41,Deals!$Q$2:$Q$41,"Signed",Deals!$F$2:$F$41,$A12)+SUMIFS(Deals!$J$2:$J$41,Deals!$Q$2:$Q$41,"Devolved",Deals!$F$2:$F$41,$A12) -> 56.818182 | D12: =IF($B$5=0,0,C12/$B$5) -> 0.009414831
A13: Sustainability-linked bond | B13: =COUNTIFS(Deals!$Q$2:$Q$41,"Priced",Deals!$F$2:$F$41,$A13)+COUNTIFS(Deals!$Q$2:$Q$41,"Signed",Deals!$F$2:$F$41,$A13)+COUNTIFS(Deals!$Q$2:$Q$41,"Devolved",Deals!$F$2:$F$41,$A13) -> 0 | C13: =SUMIFS(Deals!$J$2:$J$41,Deals!$Q$2:$Q$41,"Priced",Deals!$F$2:$F$41,$A13)+SUMIFS(Deals!$J$2:$J$41,Deals!$Q$2:$Q$41,"Signed",Deals!$F$2:$F$41,$A13)+SUMIFS(Deals!$J$2:$J$41,Deals!$Q$2:$Q$41,"Devolved",Deals!$F$2:$F$41,$A13) -> 0 | D13: =IF($B$5=0,0,C13/$B$5) -> 0
A14: Green loan | B14: =COUNTIFS(Deals!$Q$2:$Q$41,"Priced",Deals!$F$2:$F$41,$A14)+COUNTIFS(Deals!$Q$2:$Q$41,"Signed",Deals!$F$2:$F$41,$A14)+COUNTIFS(Deals!$Q$2:$Q$41,"Devolved",Deals!$F$2:$F$41,$A14) -> 7 | C14: =SUMIFS(Deals!$J$2:$J$41,Deals!$Q$2:$Q$41,"Priced",Deals!$F$2:$F$41,$A14)+SUMIFS(Deals!$J$2:$J$41,Deals!$Q$2:$Q$41,"Signed",Deals!$F$2:$F$41,$A14)+SUMIFS(Deals!$J$2:$J$41,Deals!$Q$2:$Q$41,"Devolved",Deals!$F$2:$F$41,$A14) -> 1808.4884 | D14: =IF($B$5=0,0,C14/$B$5) -> 0.29966838
A15: Sustainability-linked loan | B15: =COUNTIFS(Deals!$Q$2:$Q$41,"Priced",Deals!$F$2:$F$41,$A15)+COUNTIFS(Deals!$Q$2:$Q$41,"Signed",Deals!$F$2:$F$41,$A15)+COUNTIFS(Deals!$Q$2:$Q$41,"Devolved",Deals!$F$2:$F$41,$A15) -> 3 | C15: =SUMIFS(Deals!$J$2:$J$41,Deals!$Q$2:$Q$41,"Priced",Deals!$F$2:$F$41,$A15)+SUMIFS(Deals!$J$2:$J$41,Deals!$Q$2:$Q$41,"Signed",Deals!$F$2:$F$41,$A15)+SUMIFS(Deals!$J$2:$J$41,Deals!$Q$2:$Q$41,"Devolved",Deals!$F$2:$F$41,$A15) -> 1050 | D15: =IF($B$5=0,0,C15/$B$5) -> 0.17398608
A16: Total | B16: =SUM(B11:B15) -> 23 | C16: =SUM(C11:C15) -> 6034.9656 | D16: =SUM(D11:D15) -> 1
A18: By issuer type | B18: Deals | C18: USD mn | D18: Share
A19: Sovereign | B19: =COUNTIFS(Deals!$Q$2:$Q$41,"Priced",Deals!$D$2:$D$41,$A19)+COUNTIFS(Deals!$Q$2:$Q$41,"Signed",Deals!$D$2:$D$41,$A19)+COUNTIFS(Deals!$Q$2:$Q$41,"Devolved",Deals!$D$2:$D$41,$A19) -> 4 | C19: =SUMIFS(Deals!$J$2:$J$41,Deals!$Q$2:$Q$41,"Priced",Deals!$D$2:$D$41,$A19)+SUMIFS(Deals!$J$2:$J$41,Deals!$Q$2:$Q$41,"Signed",Deals!$D$2:$D$41,$A19)+SUMIFS(Deals!$J$2:$J$41,Deals!$Q$2:$Q$41,"Devolved",Deals!$D$2:$D$41,$A19) -> 1925.5682 | D19: =IF($B$5=0,0,C19/$B$5) -> 0.31906862
A20: PSU NBFC | B20: =COUNTIFS(Deals!$Q$2:$Q$41,"Priced",Deals!$D$2:$D$41,$A20)+COUNTIFS(Deals!$Q$2:$Q$41,"Signed",Deals!$D$2:$D$41,$A20)+COUNTIFS(Deals!$Q$2:$Q$41,"Devolved",Deals!$D$2:$D$41,$A20) -> 5 | C20: =SUMIFS(Deals!$J$2:$J$41,Deals!$Q$2:$Q$41,"Priced",Deals!$D$2:$D$41,$A20)+SUMIFS(Deals!$J$2:$J$41,Deals!$Q$2:$Q$41,"Signed",Deals!$D$2:$D$41,$A20)+SUMIFS(Deals!$J$2:$J$41,Deals!$Q$2:$Q$41,"Devolved",Deals!$D$2:$D$41,$A20) -> 1645.1136 | D20: =IF($B$5=0,0,C20/$B$5) -> 0.27259702
A21: Bank | B21: =COUNTIFS(Deals!$Q$2:$Q$41,"Priced",Deals!$D$2:$D$41,$A21)+COUNTIFS(Deals!$Q$2:$Q$41,"Signed",Deals!$D$2:$D$41,$A21)+COUNTIFS(Deals!$Q$2:$Q$41,"Devolved",Deals!$D$2:$D$41,$A21) -> 2 | C21: =SUMIFS(Deals!$J$2:$J$41,Deals!$Q$2:$Q$41,"Priced",Deals!$D$2:$D$41,$A21)+SUMIFS(Deals!$J$2:$J$41,Deals!$Q$2:$Q$41,"Signed",Deals!$D$2:$D$41,$A21)+SUMIFS(Deals!$J$2:$J$41,Deals!$Q$2:$Q$41,"Devolved",Deals!$D$2:$D$41,$A21) -> 750 | D21: =IF($B$5=0,0,C21/$B$5) -> 0.12427577
A22: Corporate | B22: =COUNTIFS(Deals!$Q$2:$Q$41,"Priced",Deals!$D$2:$D$41,$A22)+COUNTIFS(Deals!$Q$2:$Q$41,"Signed",Deals!$D$2:$D$41,$A22)+COUNTIFS(Deals!$Q$2:$Q$41,"Devolved",Deals!$D$2:$D$41,$A22) -> 9 | C22: =SUMIFS(Deals!$J$2:$J$41,Deals!$Q$2:$Q$41,"Priced",Deals!$D$2:$D$41,$A22)+SUMIFS(Deals!$J$2:$J$41,Deals!$Q$2:$Q$41,"Signed",Deals!$D$2:$D$41,$A22)+SUMIFS(Deals!$J$2:$J$41,Deals!$Q$2:$Q$41,"Devolved",Deals!$D$2:$D$41,$A22) -> 1663.1475 | D22: =IF($B$5=0,0,C22/$B$5) -> 0.27558524
A23: Municipal | B23: =COUNTIFS(Deals!$Q$2:$Q$41,"Priced",Deals!$D$2:$D$41,$A23)+COUNTIFS(Deals!$Q$2:$Q$41,"Signed",Deals!$D$2:$D$41,$A23)+COUNTIFS(Deals!$Q$2:$Q$41,"Devolved",Deals!$D$2:$D$41,$A23) -> 3 | C23: =SUMIFS(Deals!$J$2:$J$41,Deals!$Q$2:$Q$41,"Priced",Deals!$D$2:$D$41,$A23)+SUMIFS(Deals!$J$2:$J$41,Deals!$Q$2:$Q$41,"Signed",Deals!$D$2:$D$41,$A23)+SUMIFS(Deals!$J$2:$J$41,Deals!$Q$2:$Q$41,"Devolved",Deals!$D$2:$D$41,$A23) -> 51.136364 | D23: =IF($B$5=0,0,C23/$B$5) -> 0.0084733479
A24: Total | B24: =SUM(B19:B23) -> 23 | C24: =SUM(C19:C23) -> 6034.9656 | D24: =SUM(D19:D23) -> 1
A26: By year | B26: Deals | C26: USD mn | D26: Share
A27: 2023 | B27: =COUNTIFS(Deals!$Q$2:$Q$41,"Priced",Deals!$L$2:$L$41,$A27)+COUNTIFS(Deals!$Q$2:$Q$41,"Signed",Deals!$L$2:$L$41,$A27)+COUNTIFS(Deals!$Q$2:$Q$41,"Devolved",Deals!$L$2:$L$41,$A27) -> 1 | C27: =SUMIFS(Deals!$J$2:$J$41,Deals!$Q$2:$Q$41,"Priced",Deals!$L$2:$L$41,$A27)+SUMIFS(Deals!$J$2:$J$41,Deals!$Q$2:$Q$41,"Signed",Deals!$L$2:$L$41,$A27)+SUMIFS(Deals!$J$2:$J$41,Deals!$Q$2:$Q$41,"Devolved",Deals!$L$2:$L$41,$A27) -> 909.09091 | D27: =IF($B$5=0,0,C27/$B$5) -> 0.1506373
A28: 2024 | B28: =COUNTIFS(Deals!$Q$2:$Q$41,"Priced",Deals!$L$2:$L$41,$A28)+COUNTIFS(Deals!$Q$2:$Q$41,"Signed",Deals!$L$2:$L$41,$A28)+COUNTIFS(Deals!$Q$2:$Q$41,"Devolved",Deals!$L$2:$L$41,$A28) -> 5 | C28: =SUMIFS(Deals!$J$2:$J$41,Deals!$Q$2:$Q$41,"Priced",Deals!$L$2:$L$41,$A28)+SUMIFS(Deals!$J$2:$J$41,Deals!$Q$2:$Q$41,"Signed",Deals!$L$2:$L$41,$A28)+SUMIFS(Deals!$J$2:$J$41,Deals!$Q$2:$Q$41,"Devolved",Deals!$L$2:$L$41,$A28) -> 1653.4884 | D28: =IF($B$5=0,0,C28/$B$5) -> 0.27398472
A29: 2025 | B29: =COUNTIFS(Deals!$Q$2:$Q$41,"Priced",Deals!$L$2:$L$41,$A29)+COUNTIFS(Deals!$Q$2:$Q$41,"Signed",Deals!$L$2:$L$41,$A29)+COUNTIFS(Deals!$Q$2:$Q$41,"Devolved",Deals!$L$2:$L$41,$A29) -> 14 | C29: =SUMIFS(Deals!$J$2:$J$41,Deals!$Q$2:$Q$41,"Priced",Deals!$L$2:$L$41,$A29)+SUMIFS(Deals!$J$2:$J$41,Deals!$Q$2:$Q$41,"Signed",Deals!$L$2:$L$41,$A29)+SUMIFS(Deals!$J$2:$J$41,Deals!$Q$2:$Q$41,"Devolved",Deals!$L$2:$L$41,$A29) -> 2804.2045 | D29: =IF($B$5=0,0,C29/$B$5) -> 0.46465957
A30: 2026 | B30: =COUNTIFS(Deals!$Q$2:$Q$41,"Priced",Deals!$L$2:$L$41,$A30)+COUNTIFS(Deals!$Q$2:$Q$41,"Signed",Deals!$L$2:$L$41,$A30)+COUNTIFS(Deals!$Q$2:$Q$41,"Devolved",Deals!$L$2:$L$41,$A30) -> 3 | C30: =SUMIFS(Deals!$J$2:$J$41,Deals!$Q$2:$Q$41,"Priced",Deals!$L$2:$L$41,$A30)+SUMIFS(Deals!$J$2:$J$41,Deals!$Q$2:$Q$41,"Signed",Deals!$L$2:$L$41,$A30)+SUMIFS(Deals!$J$2:$J$41,Deals!$Q$2:$Q$41,"Devolved",Deals!$L$2:$L$41,$A30) -> 668.18182 | D30: =IF($B$5=0,0,C30/$B$5) -> 0.11071841
A31: Total | B31: =SUM(B27:B30) -> 23 | C31: =SUM(C27:C30) -> 6034.9656 | D31: =SUM(D27:D30) -> 1

Sheet Deals
A1: Deal ID | B1: Date | C1: Issuer / borrower | D1: Issuer type | E1: Sector | F1: Instrument | G1: Green label | H1: Currency | I1: Amount (mn, deal ccy) | J1: USD mn | K1: INR crore | L1: Year | M1: Tenor (yrs) | N1: Pricing | O1: Lenders / investors | P1: Use of proceeds / KPIs | Q1: Status | R1: Source
A2: SOV-2301 | B2: 44951 | C2: Government of India | D2: Sovereign | E2: Government | F2: Green bond | G2: Confirmed | H2: INR | I2: 80000 | J2: =IF(I2="","",I2/INDEX(FX!$B$4:$B$7,MATCH(H2,FX!$A$4:$A$7,0))) -> 909.09091 | K2: =IF(J2="","",J2*FX!$B$5/10) -> 8000 | L2: =YEAR(B2) -> 2023 | M2: 5 & 10 | N2: 7.10% (5y) / 7.29% (10y) | O2: RBI auction | P2: Debut sovereign green bonds; two tranches; eligible green expenditure under India's Sovereign Green Bond Framework | Q2: Priced | R2: Link
A3: SBI-2401 | B3: 45295 | C3: State Bank of India | D3: Bank | E3: Banking | F3: Green bond | G3: Confirmed | H3: USD | I3: 250 | J3: =IF(I3="","",I3/INDEX(FX!$B$4:$B$7,MATCH(H3,FX!$A$4:$A$7,0))) -> 250 | K3: =IF(J3="","",J3*FX!$B$5/10) -> 2200 | L3: =YEAR(B3) -> 2024 | M3: 5 | N3: SOFR + 120 bps (floating) | O3: Private placement via SBI London; MUFG sole green coordinator | P3: Senior unsecured green FRNs maturing Dec 2028; listed India INX; S&P BBB- | Q3: Priced | R3: Link
A4: TCM-2406 | B4: 45463 | C4: Tata Communications | D4: Corporate | E4: Telecom | F4: Sustainability-linked loan | G4: Confirmed | H4: USD | I4: 250 | J4: =IF(I4="","",I4/INDEX(FX!$B$4:$B$7,MATCH(H4,FX!$A$4:$A$7,0))) -> 250 | K4: =IF(J4="","",J4*FX!$B$5/10) -> 2200 | L4: =YEAR(B4) -> 2024 | M4: 5 | N4: Margin ratchet on carbon KPIs | O4: DBS; ANZ; Export Development Canada | P4: KPIs: carbon emission reduction targets supporting net zero by 2035 | Q4: Signed | R4: Link
A5: ZEL-2409 | B5: 45536 | C5: Zelestra | D5: Corporate | E5: Renewable energy | F5: Green loan | G5: Confirmed | H5: EUR | I5: 132 | J5: =IF(I5="","",I5/INDEX(FX!$B$4:$B$7,MATCH(H5,FX!$A$4:$A$7,0))) -> 153.48837 | K5: =IF(J5="","",J5*FX!$B$5/10) -> 1350.6977 | L5: =YEAR(B5) -> 2024 | O5: HSBC; Credit Agricole; MUFG; Bank of America | P5: 435 MW solar PV (Gorbea; Rajasthan) under Green Financing Framework | Q5: Signed | R5: Link
A6: AXS-2409 | B6: 45536 | C6: Axis Bank | D6: Bank | E6: Banking | F6: Green loan | G6: Confirmed | H6: USD | I6: 500 | J6: =IF(I6="","",I6/INDEX(FX!$B$4:$B$7,MATCH(H6,FX!$A$4:$A$7,0))) -> 500 | K6: =IF(J6="","",J6*FX!$B$5/10) -> 4400 | L6: =YEAR(B6) -> 2024 | O6: IFC | P6: Green and blue finance: offshore renewables; water and waste management | Q6: Signed | R6: Link
A7: REC-2409 | B7: 45562 | C7: REC Ltd | D7: PSU NBFC | E7: Power finance | F7: Green bond | G7: Confirmed | H7: USD | I7: 500 | J7: =IF(I7="","",I7/INDEX(FX!$B$4:$B$7,MATCH(H7,FX!$A$4:$A$7,0))) -> 500 | K7: =IF(J7="","",J7*FX!$B$5/10) -> 4400 | L7: =YEAR(B7) -> 2024 | M7: 5 | N7: 4.75% fixed | O7: International investors | P7: Eligible green projects under REC Green Finance Framework (CBI-aligned; Sustainable Fitch SPO); listed India INX and NSE IFSC; Baa3/BBB | Q7: Priced | R7: Link
A8: PFC-2501 | B8: 45658 | C8: Power Finance Corporation | D8: PSU NBFC | E8: Power finance | F8: Green loan | G8: Confirmed | H8: JPY | I8: 120000 | J8: =IF(I8="","",I8/INDEX(FX!$B$4:$B$7,MATCH(H8,FX!$A$4:$A$7,0))) -> 800 | K8: =IF(J8="","",J8*FX!$B$5/10) -> 7040 | L8: =YEAR(B8) -> 2025 | O8: JBIC (JPY 72 bn) + commercial banks | P8: JBIC GREEN initiative: projects reducing GHG emissions | Q8: Signed | R8: Link
A9: JKT-2501 | B9: 45678 | C9: JK Tyre & Industries | D9: Corporate | E9: Auto components | F9: Sustainability-linked loan | G9: Confirmed | H9: USD | I9: 100 | J9: =IF(I9="","",I9/INDEX(FX!$B$4:$B$7,MATCH(H9,FX!$A$4:$A$7,0))) -> 100 | K9: =IF(J9="","",J9*FX!$B$5/10) -> 880 | L9: =YEAR(B9) -> 2025 | O9: IFC | P9: PCR/TBR tyre capacity at Banmore (MP) and Laksar (UK); India's first tyre-industry SLL; KPIs not disclosed | Q9: Signed | R9: Link
A10: SOV-2501 | B10: 45688 | C10: Government of India | D10: Sovereign | E10: Government | F10: Green bond | G10: Confirmed | H10: INR | I10: 39450 | J10: =IF(I10="","",I10/INDEX(FX!$B$4:$B$7,MATCH(H10,FX!$A$4:$A$7,0))) -> 448.29545 | K10: =IF(J10="","",J10*FX!$B$5/10) -> 3945 | L10: =YEAR(B10) -> 2025 | M10: 10 | O10: Primary dealers (devolvement) | P10: 10-year sovereign green bond auction partly devolved on primary dealers (Rs 3945 crore) | Q10: Devolved | R10: Link
A11: SID-2502 | B11: 45689 | C11: SIDBI | D11: PSU NBFC | E11: MSME finance | F11: Green loan | G11: Confirmed | H11: USD | I11: 100 | J11: =IF(I11="","",I11/INDEX(FX!$B$4:$B$7,MATCH(H11,FX!$A$4:$A$7,0))) -> 100 | K11: =IF(J11="","",J11*FX!$B$5/10) -> 880 | L11: =YEAR(B11) -> 2025 | O11: Agence Francaise de Developpement | P11: Credit line to expand green finance access for MSMEs | Q11: Signed | R11: Link
A12: IRE-2503A | B12: 45737 | C12: IREDA | D12: PSU NBFC | E12: Renewable finance | F12: Green bond | G12: Unconfirmed | H12: INR | I12: 12470 | J12: =IF(I12="","",I12/INDEX(FX!$B$4:$B$7,MATCH(H12,FX!$A$4:$A$7,0))) -> 141.70455 | K12: =IF(J12="","",J12*FX!$B$5/10) -> 1247 | L12: =YEAR(B12) -> 2025 | M12: Perpetual | N12: 8.40% | O12: Institutional investors (private placement) | P12: Perpetual Tier I bonds to strengthen capital adequacy; described as green by Renewable Watch | Q12: Priced | R12: Link
A13: IRE-2503B | B13: 45741 | C13: IREDA | D13: PSU NBFC | E13: Renewable finance | F13: Green bond | G13: Unconfirmed | H13: INR | I13: 9100 | J13: =IF(I13="","",I13/INDEX(FX!$B$4:$B$7,MATCH(H13,FX!$A$4:$A$7,0))) -> 103.40909 | K13: =IF(J13="","",J13*FX!$B$5/10) -> 910 | L13: =YEAR(B13) -> 2025 | M13: 10 | N13: 7.74% | O13: Institutional investors (private placement) | P13: Tier II bonds to strengthen capital adequacy; described as green by Renewable Watch | Q13: Priced | R13: Link
A14: GZB-2504 | B14: 45748 | C14: Ghaziabad Nagar Nigam | D14: Municipal | E14: Urban water | F14: Green bond | G14: Confirmed | H14: INR | I14: 1500 | J14: =IF(I14="","",I14/INDEX(FX!$B$4:$B$7,MATCH(H14,FX!$A$4:$A$7,0))) -> 17.045455 | K14: =IF(J14="","",J14*FX!$B$5/10) -> 150 | L14: =YEAR(B14) -> 2025 | O14: Public issue | P14: Tertiary sewage treatment plant for industrial water reuse; first certified green municipal bond | Q14: Priced | R14: Link
A15: SER-2506 | B15: 45809 | C15: Serentica Renewables | D15: Corporate | E15: Renewable energy | F15: Green loan | G15: Confirmed | H15: USD | I15: 100 | J15: =IF(I15="","",I15/INDEX(FX!$B$4:$B$7,MATCH(H15,FX!$A$4:$A$7,0))) -> 100 | K15: =IF(J15="","",J15*FX!$B$5/10) -> 880 | L15: =YEAR(B15) -> 2025 | O15: Rabobank; Societe Generale | P15: 300 MW solar (Rajasthan) supplying Bharat Aluminium | Q15: Signed | R15: Link
A16: PCM-2506 | B16: 45809 | C16: Pimpri-Chinchwad Municipal Corporation | D16: Municipal | E16: Urban mobility | F16: Green bond | G16: Confirmed | H16: INR | I16: 2000 | J16: =IF(I16="","",I16/INDEX(FX!$B$4:$B$7,MATCH(H16,FX!$A$4:$A$7,0))) -> 22.727273 | K16: =IF(J16="","",J16*FX!$B$5/10) -> 200 | L16: =YEAR(B16) -> 2025 | O16: Public issue (5x oversubscribed); BSE listed | P16: Sustainable mobility projects; Rs 20 crore Urban Challenge Fund incentive | Q16: Priced | R16: Link
A17: LTB-2506 | B17: 45809 | C17: Larsen & Toubro | D17: Corporate | E17: Engineering & construction | F17: ESG bond | G17: Confirmed | H17: INR | I17: 5000 | J17: =IF(I17="","",I17/INDEX(FX!$B$4:$B$7,MATCH(H17,FX!$A$4:$A$7,0))) -> 56.818182 | K17: =IF(J17="","",J17*FX!$B$5/10) -> 500 | L17: =YEAR(B17) -> 2025 | M17: 3 | N17: 6.35% | O17: Domestic investors | P17: ESG-labelled bonds | Q17: Priced | R17: Link
A18: IGR-2506 | B18: 45809 | C18: IndiGrid | D18: Corporate | E18: Power transmission / storage | F18: Green loan | G18: Confirmed | H18: USD | I18: 55 | J18: =IF(I18="","",I18/INDEX(FX!$B$4:$B$7,MATCH(H18,FX!$A$4:$A$7,0))) -> 55 | K18: =IF(J18="","",J18*FX!$B$5/10) -> 484 | L18: =YEAR(B18) -> 2025 | N18: Part concessional (USD 16.5 mn CTF) | O18: IFC; Clean Technology Fund | P18: 180 MW / 360 MWh standalone battery storage (Gujarat) | Q18: Signed | R18: Link
A19: SOV-2506 | B19: 45821 | C19: Government of India | D19: Sovereign | E19: Government | F19: Green bond | G19: Confirmed | H19: INR | I19: 0 | J19: =IF(I19="","",I19/INDEX(FX!$B$4:$B$7,MATCH(H19,FX!$A$4:$A$7,0))) -> 0 | K19: =IF(J19="","",J19*FX!$B$5/10) -> 0 | L19: =YEAR(B19) -> 2025 | M19: 30 | N19: Bids rejected | O19: RBI auction | P19: Rs 5000 crore 30-year reissue: all bids rejected as investors sought higher yields | Q19: Rejected | R19: Link
A20: ABC-2508 | B20: 45870 | C20: Aditya Birla Capital | D20: Corporate | E20: NBFC | F20: Green bond | G20: Confirmed | H20: INR | I20: 13010 | J20: =IF(I20="","",I20/INDEX(FX!$B$4:$B$7,MATCH(H20,FX!$A$4:$A$7,0))) -> 147.84091 | K20: =IF(J20="","",J20*FX!$B$5/10) -> 1301 | L20: =YEAR(B20) -> 2025 | O20: Asian Infrastructure Investment Bank | P20: NCDs for clean energy (solar; wind; hydrogen; storage) and e-mobility lending | Q20: Priced | R20: Link
A21: LTS-2509 | B21: 45929 | C21: Larsen & Toubro | D21: Corporate | E21: Engineering & construction | F21: Sustainability-linked loan | G21: Confirmed | H21: USD | I21: 700 | J21: =IF(I21="","",I21/INDEX(FX!$B$4:$B$7,MATCH(H21,FX!$A$4:$A$7,0))) -> 700 | K21: =IF(J21="","",J21*FX!$B$5/10) -> 6160 | L21: =YEAR(B21) -> 2025 | N21: KPI-linked pricing | O21: Standard Chartered | P21: Sustainability-linked trade facility; KPIs: GHG emission intensity and fresh-water withdrawal | Q21: Signed | R21: Link
A22: SUR-2510 | B22: 45936 | C22: Surat Municipal Corporation | D22: Municipal | E22: Urban infrastructure | F22: Green bond | G22: Confirmed | H22: INR | I22: 1000 | J22: =IF(I22="","",I22/INDEX(FX!$B$4:$B$7,MATCH(H22,FX!$A$4:$A$7,0))) -> 11.363636 | K22: =IF(J22="","",J22*FX!$B$5/10) -> 100 | L22: =YEAR(B22) -> 2025 | M22: 4 & 5 | N22: 8.00% (STRPP A and B) | O22: Public issue; A. K. Capital (lead manager) | P22: Solar plant; wind plant; e-bus depot; waste processing; water treatment; intake well. Base Rs 100 cr (greenshoe up to Rs 100 cr more; final allotment not confirmed); AA+ (CRISIL / Ind-Ra) | Q22: Priced | R22: Link
A23: SOV-2604 | B23: 46136 | C23: Government of India | D23: Sovereign | E23: Government | F23: Green bond | G23: Confirmed | H23: INR | J23: =IF(I23="","",I23/INDEX(FX!$B$4:$B$7,MATCH(H23,FX!$A$4:$A$7,0))) | K23: =IF(J23="","",J23*FX!$B$5/10) | L23: =YEAR(B23) -> 2026 | M23: 30 | N23: 7.50% coupon; ~6 bps greenium; ~2.5x bid-cover | O23: Insurers (state-run and private) | P23: 30-year green bond; largest greenium since Jan 2023; amount not reported | Q23: Priced | R23: Link
A24: SOV-2608 | B24: 46248 | C24: Government of India | D24: Sovereign | E24: Government | F24: Green bond | G24: Confirmed | H24: INR | I24: 50000 | J24: =IF(I24="","",I24/INDEX(FX!$B$4:$B$7,MATCH(H24,FX!$A$4:$A$7,0))) -> 568.18182 | K24: =IF(J24="","",J24*FX!$B$5/10) -> 5000 | L24: =YEAR(B24) -> 2026 | M24: 30 | N24: ~4 bps greenium | O24: RBI auction | P24: Rs 5000 crore 30-year; outstanding sovereign green bonds Rs 877 bn after this sale | Q24: Priced | R24: Link
A25: SOV-27H2 | B25: 46296 | C25: Government of India | D25: Sovereign | E25: Government | F25: Green bond | G25: Confirmed | H25: INR | I25: 150000 | J25: =IF(I25="","",I25/INDEX(FX!$B$4:$B$7,MATCH(H25,FX!$A$4:$A$7,0))) -> 1704.5455 | K25: =IF(J25="","",J25*FX!$B$5/10) -> 15000 | L25: =YEAR(B25) -> 2026 | M25: 30 | N25: Greenshoe up to Rs 2000 cr per auction | O25: RBI auctions (5 x Rs 3000 cr) | P25: H2 FY27 borrowing calendar: five 30-year tranches; 5% reserved for retail | Q25: Scheduled | R25: Link
A26: REN-2610 | B26: 46308 | C26: ReNew Solar Power | D26: Corporate | E26: Renewable energy | F26: Green loan | G26: Confirmed | H26: USD | I26: 100 | J26: =IF(I26="","",I26/INDEX(FX!$B$4:$B$7,MATCH(H26,FX!$A$4:$A$7,0))) -> 100 | K26: =IF(J26="","",J26*FX!$B$5/10) -> 880 | L26: =YEAR(B26) -> 2026 | M26: 10 | N26: INR-denominated | O26: FMO | P26: Solar and hybrid project expansion; FMO classifies 100% as green | Q26: Signed | R26: Link
J27: =IF(I27="","",I27/INDEX(FX!$B$4:$B$7,MATCH(H27,FX!$A$4:$A$7,0))) | K27: =IF(J27="","",J27*FX!$B$5/10) | L27: =IF(B27="","",YEAR(B27))
J28: =IF(I28="","",I28/INDEX(FX!$B$4:$B$7,MATCH(H28,FX!$A$4:$A$7,0))) | K28: =IF(J28="","",J28*FX!$B$5/10) | L28: =IF(B28="","",YEAR(B28))
J29: =IF(I29="","",I29/INDEX(FX!$B$4:$B$7,MATCH(H29,FX!$A$4:$A$7,0))) | K29: =IF(J29="","",J29*FX!$B$5/10) | L29: =IF(B29="","",YEAR(B29))
J30: =IF(I30="","",I30/INDEX(FX!$B$4:$B$7,MATCH(H30,FX!$A$4:$A$7,0))) | K30: =IF(J30="","",J30*FX!$B$5/10) | L30: =IF(B30="","",YEAR(B30))
J31: =IF(I31="","",I31/INDEX(FX!$B$4:$B$7,MATCH(H31,FX!$A$4:$A$7,0))) | K31: =IF(J31="","",J31*FX!$B$5/10) | L31: =IF(B31="","",YEAR(B31))
J32: =IF(I32="","",I32/INDEX(FX!$B$4:$B$7,MATCH(H32,FX!$A$4:$A$7,0))) | K32: =IF(J32="","",J32*FX!$B$5/10) | L32: =IF(B32="","",YEAR(B32))
J33: =IF(I33="","",I33/INDEX(FX!$B$4:$B$7,MATCH(H33,FX!$A$4:$A$7,0))) | K33: =IF(J33="","",J33*FX!$B$5/10) | L33: =IF(B33="","",YEAR(B33))
J34: =IF(I34="","",I34/INDEX(FX!$B$4:$B$7,MATCH(H34,FX!$A$4:$A$7,0))) | K34: =IF(J34="","",J34*FX!$B$5/10) | L34: =IF(B34="","",YEAR(B34))
J35: =IF(I35="","",I35/INDEX(FX!$B$4:$B$7,MATCH(H35,FX!$A$4:$A$7,0))) | K35: =IF(J35="","",J35*FX!$B$5/10) | L35: =IF(B35="","",YEAR(B35))
J36: =IF(I36="","",I36/INDEX(FX!$B$4:$B$7,MATCH(H36,FX!$A$4:$A$7,0))) | K36: =IF(J36="","",J36*FX!$B$5/10) | L36: =IF(B36="","",YEAR(B36))
J37: =IF(I37="","",I37/INDEX(FX!$B$4:$B$7,MATCH(H37,FX!$A$4:$A$7,0))) | K37: =IF(J37="","",J37*FX!$B$5/10) | L37: =IF(B37="","",YEAR(B37))
J38: =IF(I38="","",I38/INDEX(FX!$B$4:$B$7,MATCH(H38,FX!$A$4:$A$7,0))) | K38: =IF(J38="","",J38*FX!$B$5/10) | L38: =IF(B38="","",YEAR(B38))
... J41: =IF(I41="","",I41/INDEX(FX!$B$4:$B$7,MATCH(H41,FX!$A$4:$A$7,0))) | K41: =IF(J41="","",J41*FX!$B$5/10) | L41: =IF(B41="","",YEAR(B41))

Sheet FX
A1: FX assumptions (units per 1 USD)
A2: Approximate October 2026 levels. Blue cells are inputs: edit to re-price every deal.
A3: Currency | B3: Per USD
A4: USD | B4: 1
A5: INR | B5: 88
A6: EUR | B6: 0.86
A7: JPY | B7: 150

Sheet Sovereign Greenium
A1: Sovereign green bonds: auction outcomes and greenium
A2: Greenium = yield discount vs a comparable conventional G-sec, in basis points. Blank where the source gives none.
A4: Auction | B4: Tenor | C4: Notified (INR cr) | D4: Outcome | E4: Greenium (bps) | F4: What it tells you | G4: Source
A5: Jan 2023 | B5: 5y / 10y | C5: 8000 | D5: Debut; >4x subscribed | E5: 6 | F5: Strong debut demand, priced through conventional curve | G5: Link
A6: May 2024 | C6: 6000 | D6: Cancelled: no pricing advantage | F6: Government refused to issue without a greenium | G6: Link
A7: Aug 2024 | C7: 6000 | D7: Only Rs 1,697 cr bid; cut-off 6.90% | F7: Thin demand at short/medium tenors | G7: Link
A8: Nov 2024 | C8: 5000 | D8: 70% devolved on primary dealers (6.78-6.84%) | F8: Banks unwilling to pay a greenium | G8: Link
A9: Jan 2025 | B9: 10y | D9: Rs 3,945 cr devolved on primary dealers | F9: 10-year green paper struggles | G9: Link
A10: Jun 2025 | B10: 30y | C10: 5000 | D10: All bids rejected | F10: Investors sought higher yields than the government would pay | G10: Link
A11: Apr 2026 | B11: 30y | D11: ~2.5x subscribed; 7.50% coupon | E11: 6 | F11: Largest greenium since 2023; insurers drive demand via 'infra' classification | G11: Link
A12: Aug 2026 | B12: 30y | C12: 5000 | D12: Sold in full | E12: 4 | F12: H1 FY27 average greenium 4 bps, highest since launch | G12: Link
A13: Oct 2026 - Jan 2027 | B13: 30y | C13: 15000 | D13: Scheduled: 5 x Rs 3,000 cr | F13: Government shifted green supply to 30-year, where demand exists | G13: Link
D14: Average greenium where reported (bps) | E14: =AVERAGE(E5:E13) -> 5.3333333

Sheet About
A1: About this tracker
A2: Scope: labelled green, ESG and sustainability-linked bonds and loans by Indian issuers and borrowers, plus sovereign green bond auctions, Jan 2023 to Oct 2026. Every deal row links to its public source.
A3: Inputs: blue text on yellow is editable. Add a deal in the empty yellow rows at the bottom of the Deals sheet; USD, INR crore and every Dashboard figure update automatically.
A4: Completed = Priced, Signed or Devolved. Rejected and Scheduled deals are listed but not counted in totals.
A5: Green label 'Unconfirmed' = the issuer is a green-sector lender and a trade publication calls the issue green, but the issuer's own release does not. Treat with caution.
A6: FX: deals are converted at the FX sheet's rates, not the historical rate on each deal date, so totals are indicative.
A7: Limits: this is a curated sample from public news and filings, not a complete market database (e.g. Bloomberg, LSEG, CBI). Amounts not disclosed by the source are left blank and excluded from totals.
A9: Prepared by Mayank Majoka, October 2026. Not investment advice.
